{
  "flow-id": "first-launch",
  "version": 1,
  "steps": [
    {
      "id": "welcome",
      "title": "欢迎使用 Liii STEM",
      "top-text": "",
      "bubble-size": "medium",
      "offset-x": 0,
      "offset-y": 0,
      "media-path": "",
      "bottom-text": "这是 Liii STEM 的主工作区。教程会依次介绍几个核心功能，帮助您快速上手。",
      "target-id": "",
      "placement": "bottom",
      "highlight-padding": 0,
      "on-enter": "",
      "skip-if-missing": true
    },
    {
      "id": "magic-paste",
      "title": "魔法粘贴",
      "top-text": "魔法粘贴可以自动识别剪贴板中的内容类型，并尽可能保留网页内容的结构、标题层级、列表样式和公式表达，让外部内容进入文档后依然便于继续编辑与排版。",
      "bubble-size": "large",
      "offset-x": 500,
      "offset-y": 0,
      "media-path": ":/tutorial/magic-paste-tutorial.gif",
      "bottom-text": "<b>系统已经为您打开了一个新的空白文档，并将一段网页内容复制到了剪贴板。</b>请在编辑区中使用 <b>Ctrl+V</b>（Windows / Linux）或 <b>Command+V</b>（macOS）进行粘贴。完成本步操作后，才可以进入下一步。",
      "target-id": "editorArea",
      "placement": "top",
      "highlight-padding": 12,
      "require-action": "paste",
      "on-enter": "(tutorial-prepare-magic-paste-demo)",
      "skip-if-missing": true
    },
    {
      "id": "ocr",
      "title": "OCR 文字识别",
      "top-text": "如果您的剪贴板中包含图片内容，软件可以通过快捷键触发 OCR ，提取其中的文字，让您快速将截图转换为可编辑文本；您也可以在插入图片后，通过图片悬浮菜单上的 OCR 按钮发起识别。",
      "bubble-size": "large",
      "offset-x": 500,
      "offset-y": 0,
      "media-path": ":/tutorial/ocr-tutorial.gif",
      "bottom-text": "系统已经为您打开了一个包含图片的文档，且将一张图片放入了您的剪贴板，您可以在编辑区中使用 <b>Ctrl+Shift+V</b>（Windows / Linux）或 <b>Command+Shift+V</b>（macOS）触发 OCR 识别，也可以用鼠标点击悬浮菜单中的按钮触发 OCR 识别，图片中的文字将被快速提取为文档中的可编辑文本。完成本步操作后，才可以进入下一步。",
      "target-id": "editorArea",
      "placement": "top",
      "highlight-padding": 12,
      "require-action": "ocr-paste",
      "on-enter": "(tutorial-prepare-ocr-demo)",
      "skip-if-missing": true
    }
  ]
}
